odoo/addons/partner_multi_company_pos/README.rst
odoo/addons/partner_multi_company_pos/__init__.py
odoo/addons/partner_multi_company_pos/__manifest__.py
odoo/addons/partner_multi_company_pos/i18n/it.po
odoo/addons/partner_multi_company_pos/i18n/it_IT.po
odoo/addons/partner_multi_company_pos/i18n/partner_multi_company_pos.pot
odoo/addons/partner_multi_company_pos/models/__init__.py
odoo/addons/partner_multi_company_pos/models/res_partner.py
odoo/addons/partner_multi_company_pos/readme/CONTRIBUTORS.rst
odoo/addons/partner_multi_company_pos/readme/DESCRIPTION.rst
odoo/addons/partner_multi_company_pos/static/description/icon.png
odoo/addons/partner_multi_company_pos/static/description/index.html
odoo14_addon_partner_multi_company_pos-14.0.1.0.1.dev6.dist-info/METADATA
odoo14_addon_partner_multi_company_pos-14.0.1.0.1.dev6.dist-info/WHEEL
odoo14_addon_partner_multi_company_pos-14.0.1.0.1.dev6.dist-info/top_level.txt
odoo14_addon_partner_multi_company_pos-14.0.1.0.1.dev6.dist-info/RECORD
