Metadata-Version: 2.1
Name: odoo14-addon-partner_multi_company_pos
Version: 14.0.1.0.1.dev6
Summary: Partner Multi Company POS
Home-page: https://github.com/OCA/multi-company
Author: PyTech SRL, Odoo Community Association (OCA)
Author-email: support@odoo-community.org
License: AGPL-3
Classifier: Programming Language :: Python
Classifier: Framework :: Odoo
Classifier: Framework :: Odoo :: 14.0
Classifier: License :: OSI Approved :: GNU Affero General Public License v3
Requires-Python: >=3.6
Requires-Dist: odoo14-addon-partner-multi-company
Requires-Dist: odoo<14.1dev,>=14.0a
